arch_ops_server/__init__.py
arch_ops_server/aur.py
arch_ops_server/config.py
arch_ops_server/http_server.py
arch_ops_server/logs.py
arch_ops_server/mirrors.py
arch_ops_server/news.py
arch_ops_server/pacman.py
arch_ops_server/py.typed
arch_ops_server/server.py
arch_ops_server/system.py
arch_ops_server/tool_metadata.py
arch_ops_server/utils.py
arch_ops_server/wiki.py
arch_ops_server-3.1.0.dist-info/WHEEL
arch_ops_server-3.1.0.dist-info/entry_points.txt
arch_ops_server-3.1.0.dist-info/METADATA
arch_ops_server-3.1.0.dist-info/RECORD
