Metadata-Version: 2.3
Name: arch-ops-server
Version: 3.1.0
Summary: MCP server bridging AI assistants with Arch Linux ecosystem (Wiki, AUR, official repos)
Keywords: arch-linux,mcp,model-context-protocol,aur,pacman,wiki,ai-assistant
Author: Nihal
Author-email: Nihal <2tv8xupqg@mozmail.com>
License: GPL-3.0-only OR MIT
Classifier: Development Status :: 4 - Beta
Classifier: Intended Audience :: Developers
Classifier: Intended Audience :: System Administrators
Classifier: License :: OSI Approved :: GNU General Public License v3 (GPLv3)
Classifier: License :: OSI Approved :: MIT License
Classifier: Operating System :: POSIX :: Linux
Classifier: Programming Language :: Python :: 3
Classifier: Programming Language :: Python :: 3.11
Classifier: Programming Language :: Python :: 3.12
Classifier: Topic :: System :: Archiving :: Packaging
Classifier: Topic :: System :: Systems Administration
Requires-Dist: mcp>=1.0.0
Requires-Dist: httpx>=0.27.0
Requires-Dist: beautifulsoup4>=4.12.0
Requires-Dist: lxml>=5.0.0
Requires-Dist: markdownify>=0.12.0
Requires-Dist: pytest>=8.0.0 ; extra == 'dev'
Requires-Dist: pytest-asyncio>=0.23.0 ; extra == 'dev'
Requires-Dist: pytest-cov>=4.1.0 ; extra == 'dev'
Requires-Dist: pytest-mock>=3.12.0 ; extra == 'dev'
Requires-Dist: httpx>=0.27.0 ; extra == 'dev'
Requires-Dist: starlette>=0.27.0 ; extra == 'http'
Requires-Dist: uvicorn[standard]>=0.23.0 ; extra == 'http'
Requires-Python: >=3.11
Provides-Extra: dev
Provides-Extra: http
